logentry_admin/__init__.py
logentry_admin/admin.py
logentry_admin/models.py
logentry_admin/templates/admin/admin/logentry/change_form.html
django_logentry_admin-1.1.0.dist-info/LICENSE.txt
django_logentry_admin-1.1.0.dist-info/METADATA
django_logentry_admin-1.1.0.dist-info/WHEEL
django_logentry_admin-1.1.0.dist-info/top_level.txt
django_logentry_admin-1.1.0.dist-info/RECORD
